json_codec/__init__.py
json_codec/codecs/__init__.py
json_codec/codecs/date_codec.py
json_codec/codecs/datetime_codec.py
json_codec/codecs/dict_codec.py
json_codec/codecs/list_codec.py
json_codec/codecs/primitive_codec.py
json_codec/codecs/set_codec.py
json_codec/codecs/time_codec.py
json_codec/codecs/tuple_codec.py
json_codec/codecs/union_codec.py
json_codec/json_codec.py
json_codec/py.typed
json_codec/test_json_codec.py
json_codec/types.py
json_codec/utils.py
json_codec-0.3.0.dist-info/METADATA
json_codec-0.3.0.dist-info/WHEEL
json_codec-0.3.0.dist-info/RECORD
