Metadata-Version: 2.1
Name: json-codec
Version: 0.3.0
Summary: 
Home-page: https://github.com/LuscasLeo/json_codec
Author: Lucas Silva
Author-email: lucas76leonardo@gmail.com
Requires-Python: >=3.7,<4.0
Classifier: Programming Language :: Python :: 3
Classifier: Programming Language :: Python :: 3.7
Classifier: Programming Language :: Python :: 3.8
Classifier: Programming Language :: Python :: 3.9
Classifier: Programming Language :: Python :: 3.10
Classifier: Programming Language :: Python :: 3.11
Project-URL: Repository, https://github.com/LuscasLeo/json_codec
